langlab/__init__.py
langlab/__main__.py
langlab/main.py
langlab/parsemk.py
langlab/pymake/__init__.py
langlab/pymake/command.py
langlab/pymake/data.py
langlab/pymake/errors.py
langlab/pymake/functions.py
langlab/pymake/globrelative.py
langlab/pymake/implicit.py
langlab/pymake/parser.py
langlab/pymake/parserdata.py
langlab/pymake/process.py
langlab/pymake/util.py
langlab-0.3.0.dist-info/LICENSE
langlab-0.3.0.dist-info/METADATA
langlab-0.3.0.dist-info/WHEEL
langlab-0.3.0.dist-info/entry_points.txt
langlab-0.3.0.dist-info/top_level.txt
langlab-0.3.0.dist-info/RECORD
