Metadata-Version: 2.1
Name: langlab
Version: 0.3.0
Summary: Microapp project for programming languages
Home-page: UNKNOWN
Author: Youngsung Kim
Author-email: youngsung.kim.act2@gmail.com
License: UNKNOWN
Project-URL: Bug Reports, https://github.com/grnydawn/langlab/issues
Project-URL: Source, https://github.com/grnydawn/langlab
Keywords: langlab
Platform: UNKNOWN
Classifier: Development Status :: 3 - Alpha
Classifier: Intended Audience :: Science/Research
Classifier: Topic :: Scientific/Engineering
Classifier: License :: OSI Approved :: MIT License
Classifier: Programming Language :: Python :: 3
Classifier: Programming Language :: Python :: 3.5
Classifier: Programming Language :: Python :: 3.6
Classifier: Programming Language :: Python :: 3.7
Classifier: Programming Language :: Python :: 3.8
Requires-Dist: microapp (>=0.2.5)
